alerk_pack/__init__.py
alerk_pack/communicator.py
alerk_pack/crypto.py
alerk_pack/message.py
alerk_pack-0.4.0.dist-info/licenses/LICENSE
alerk_pack-0.4.0.dist-info/METADATA
alerk_pack-0.4.0.dist-info/WHEEL
alerk_pack-0.4.0.dist-info/top_level.txt
alerk_pack-0.4.0.dist-info/RECORD
