Metadata-Version: 2.4
Name: alerk_pack
Version: 0.4.0
Summary: alerk functions and utilities.
Author-email: The220th <The220th@gmail.com>
License-Expression: MIT
Project-URL: Homepage, https://github.com/The220th/alerk_pack
Project-URL: Issues, https://github.com/The220th/alerk_pack/issues
Classifier: Programming Language :: Python :: 3
Classifier: Operating System :: OS Independent
Requires-Python: >=3.7
License-File: LICENSE
Requires-Dist: ksupk
Requires-Dist: cryptography
Requires-Dist: pydantic
Requires-Dist: requests
Dynamic: license-file
